<?xml version="1.0" encoding="UTF-8"?>
<CommandInterface xmlns="http://v8.1c.ru/8.3/xcf/extrnprops" xmlns:xr="http://v8.1c.ru/8.3/xcf/readable" xmlns:xs="http://www.w3.org/2001/XMLSchema" xmlns:xsi="http://www.w3.org/2001/XMLSchema-instance">
	<CommandsVisibility>
		<Command name="Document.ВнутреннееПотреблениеТоваров.StandardCommand.OpenList">
			<Visibility>
				<xr:Common>false</xr:Common>
			</Visibility>
		</Command>
		<Command name="Document.ПеремещениеТоваров.StandardCommand.OpenList">
			<Visibility>
				<xr:Common>false</xr:Common>
			</Visibility>
		</Command>
		<Command name="Document.СборкаТоваров.StandardCommand.OpenList">
			<Visibility>
				<xr:Common>false</xr:Common>
			</Visibility>
		</Command>
		<Command name="Document.ЗаказНаВнутреннееПотребление.StandardCommand.Create">
			<Visibility>
				<xr:Common>true</xr:Common>
			</Visibility>
		</Command>
		<Command name="Document.ЗаказНаПеремещение.StandardCommand.Create">
			<Visibility>
				<xr:Common>true</xr:Common>
			</Visibility>
		</Command>
		<Command name="Document.ЗаказНаСборку.StandardCommand.Create">
			<Visibility>
				<xr:Common>true</xr:Common>
			</Visibility>
		</Command>
		<Command name="Report.ИсполнениеРаспоряженийНаПеремещениеСборку.StandardCommand.Open">
			<Visibility>
				<xr:Common>false</xr:Common>
			</Visibility>
		</Command>
		<Command name="Report.МатериалыВЭксплуатации.StandardCommand.Open">
			<Visibility>
				<xr:Common>false</xr:Common>
			</Visibility>
		</Command>
	</CommandsVisibility>
	<CommandsPlacement>
		<Command name="Document.ВнутреннееПотреблениеТоваров.StandardCommand.OpenList">
			<CommandGroup>NavigationPanelSeeAlso</CommandGroup>
			<Placement>Auto</Placement>
		</Command>
		<Command name="Document.ПеремещениеТоваров.StandardCommand.OpenList">
			<CommandGroup>NavigationPanelSeeAlso</CommandGroup>
			<Placement>Auto</Placement>
		</Command>
		<Command name="Document.СборкаТоваров.StandardCommand.OpenList">
			<CommandGroup>NavigationPanelSeeAlso</CommandGroup>
			<Placement>Auto</Placement>
		</Command>
	</CommandsPlacement>
	<CommandsOrder>
		<Command name="Document.ЗаказНаВнутреннееПотребление.StandardCommand.OpenList">
			<CommandGroup>NavigationPanelOrdinary</CommandGroup>
		</Command>
		<Command name="Document.ЗаказНаПеремещение.StandardCommand.OpenList">
			<CommandGroup>NavigationPanelOrdinary</CommandGroup>
		</Command>
		<Command name="Document.ЗаказНаСборку.StandardCommand.OpenList">
			<CommandGroup>NavigationPanelOrdinary</CommandGroup>
		</Command>
		<Command name="Document.ВнутреннееПотреблениеТоваров.Command.ВнутренниеПотребленияТоваров">
			<CommandGroup>NavigationPanelOrdinary</CommandGroup>
		</Command>
		<Command name="Document.ПеремещениеТоваров.Command.ПеремещенияТоваров">
			<CommandGroup>NavigationPanelOrdinary</CommandGroup>
		</Command>
		<Command name="Document.СборкаТоваров.Command.СборкиРазборкиТоваров">
			<CommandGroup>NavigationPanelOrdinary</CommandGroup>
		</Command>
		<Command name="Document.ПрочееОприходованиеТоваров.StandardCommand.OpenList">
			<CommandGroup>NavigationPanelOrdinary</CommandGroup>
		</Command>
		<Command name="Document.ВнутреннееПотреблениеТоваров.StandardCommand.OpenList">
			<CommandGroup>NavigationPanelSeeAlso</CommandGroup>
		</Command>
		<Command name="Document.ПеремещениеТоваров.StandardCommand.OpenList">
			<CommandGroup>NavigationPanelSeeAlso</CommandGroup>
		</Command>
		<Command name="Document.СборкаТоваров.StandardCommand.OpenList">
			<CommandGroup>NavigationPanelSeeAlso</CommandGroup>
		</Command>
	</CommandsOrder>
	<GroupsOrder>
		<Group>NavigationPanelOrdinary</Group>
		<Group>NavigationPanelSeeAlso</Group>
	</GroupsOrder>
</CommandInterface>